structure/__init__.py
structure/authentication.py
structure/config.py
structure/deploy.py
structure/errors.py
structure/help.py
structure/lifecycle.py
structure/network.py
structure/structure.py
structure/update.py
structure/utils.py
structure-0.1.dev16.dist-info/METADATA
structure-0.1.dev16.dist-info/RECORD
structure-0.1.dev16.dist-info/WHEEL
structure-0.1.dev16.dist-info/entry_points.txt
structure-0.1.dev16.dist-info/top_level.txt
