Metadata-Version: 2.1
Name: structure
Version: 0.1.dev16
Summary: The Structure CLI (Command-Line Tool).
Home-page: https://structure.sh
Author: Structural Labs, Inc.
Author-email: help@structure.sh
License: UNKNOWN
Platform: UNKNOWN
Requires-Dist: fire
Requires-Dist: pyyaml
Requires-Dist: requests
Requires-Dist: colorama
Requires-Dist: tinynetrc
Requires-Dist: requests[security]
Requires-Dist: pathspec
Requires-Dist: pipdate (==0.3.1)
